odoo/addons/l10n_es_pos/README.rst
odoo/addons/l10n_es_pos/__init__.py
odoo/addons/l10n_es_pos/__manifest__.py
odoo/addons/l10n_es_pos/hooks.py
odoo/addons/l10n_es_pos/i18n/ca.po
odoo/addons/l10n_es_pos/i18n/ca_ES.po
odoo/addons/l10n_es_pos/i18n/es.po
odoo/addons/l10n_es_pos/i18n/l10n_es_pos.pot
odoo/addons/l10n_es_pos/models/__init__.py
odoo/addons/l10n_es_pos/models/ir_sequence.py
odoo/addons/l10n_es_pos/models/pos_config.py
odoo/addons/l10n_es_pos/models/pos_order.py
odoo/addons/l10n_es_pos/readme/CONFIGURE.rst
odoo/addons/l10n_es_pos/readme/CONTRIBUTORS.rst
odoo/addons/l10n_es_pos/readme/DESCRIPTION.rst
odoo/addons/l10n_es_pos/readme/INSTALL.rst
odoo/addons/l10n_es_pos/readme/ROADMAP.rst
odoo/addons/l10n_es_pos/static/description/icon.png
odoo/addons/l10n_es_pos/static/description/index.html
odoo/addons/l10n_es_pos/static/src/js/models.js
odoo/addons/l10n_es_pos/static/src/js/screens.js
odoo/addons/l10n_es_pos/static/src/xml/pos.xml
odoo/addons/l10n_es_pos/views/pos_templates.xml
odoo/addons/l10n_es_pos/views/pos_views.xml
odoo13_addon_l10n_es_pos-13.0.1.2.0.dist-info/METADATA
odoo13_addon_l10n_es_pos-13.0.1.2.0.dist-info/WHEEL
odoo13_addon_l10n_es_pos-13.0.1.2.0.dist-info/top_level.txt
odoo13_addon_l10n_es_pos-13.0.1.2.0.dist-info/RECORD
